exchange/__init__.py
exchange/checkpoint.py
exchange/content.py
exchange/exchange.py
exchange/invalid_choice_error.py
exchange/langfuse_wrapper.py
exchange/message.py
exchange/token_usage_collector.py
exchange/tool.py
exchange/utils.py
exchange/moderators/__init__.py
exchange/moderators/base.py
exchange/moderators/passive.py
exchange/moderators/summarizer.jinja
exchange/moderators/summarizer.py
exchange/moderators/truncate.py
exchange/providers/__init__.py
exchange/providers/anthropic.py
exchange/providers/azure.py
exchange/providers/base.py
exchange/providers/bedrock.py
exchange/providers/databricks.py
exchange/providers/google.py
exchange/providers/groq.py
exchange/providers/ollama.py
exchange/providers/openai.py
exchange/providers/utils.py
ai_exchange-0.9.9.dist-info/METADATA
ai_exchange-0.9.9.dist-info/WHEEL
ai_exchange-0.9.9.dist-info/entry_points.txt
ai_exchange-0.9.9.dist-info/RECORD
