Metadata-Version: 2.3
Name: ai-exchange
Version: 0.9.9
Summary: a uniform python SDK for message generation with LLMs
Requires-Python: >=3.10
Requires-Dist: attrs>=24.2.0
Requires-Dist: griffe>=1.1.1
Requires-Dist: httpx>=0.27.0
Requires-Dist: jinja2>=3.1.4
Requires-Dist: langfuse>=2.38.2
Requires-Dist: python-dotenv>=1.0.1
Requires-Dist: tenacity>=9.0.0
Requires-Dist: tiktoken>=0.8.0
